earthworm/__init__.py
earthworm/timeseries_utils.py
earthworm-0.0.1.dist-info/METADATA
earthworm-0.0.1.dist-info/WHEEL
earthworm-0.0.1.dist-info/licenses/LICENSE
earthworm-0.0.1.dist-info/RECORD
