Metadata-Version: 2.1
Name: earthworm
Version: 0.0.1
Summary: Some utils for preocessing timeseries data.
Project-URL: Homepage, https://gitee.com/frozencookie/earthworm
Project-URL: Bug Tracker, https://gitee.com/frozencookie/earthworm/issues
Author-email: frozencookie <cookie.monster.yan@hotmail.com>
License:                     GNU GENERAL PUBLIC LICENSE
Classifier: License :: OSI Approved :: GNU General Public License v3 (GPLv3)
Classifier: Operating System :: OS Independent
Classifier: Programming Language :: Python :: 3
Requires-Python: >=3.6
